[
  {
    "index": 1,
    "name": "Resorts World Casino",
    "id": "Resorts_World_Casino",
    "openDate": "11am - 5am"
  },
  {
    "index": 2,
    "name": "Genting Casino Birmingham",
    "id": "Genting_Casino_Birmingham",
    "openDate": "11am - 6am"
  },
  {
    "index": 3,
    "name": "Grosvenor Casino Birmingham",
    "id": "Grosvenor_Casino_Birmingham",
    "openDate": "Open 24 hours"
  },
  {
    "index": 4,
    "name": "Rainbow Casino Birmingham",
    "id": "Rainbow_Casino_Birmingham",
    "openDate": "2pm - 6am"
  },
  {
    "index": 5,
    "name": "Shaftesbury Casino West Bromwich",
    "id": "Shaftesbury_Casino_West_Bromwich",
    "openDate": "11am - 5am"
  },
  {
    "index": 6,
    "name": "Mecca Acocks Green",
    "id": "Mecca_Acocks_Green",
    "openDate": "11am - 12am"
  },
  {
    "index": 7,
    "name": "Merkur Slots Erdington",
    "id": "Merkur_Slots_Erdington",
    "openDate": "Open 24 hrs."
  }
]
